sunspecdemo/__init__.py
sunspecdemo/cli.py
sunspecdemo/clishared.py
sunspecdemo/datalogger.py
sunspecdemo/demos.py
sunspecdemo/models.py
sunspecdemo/read.py
sunspecdemo/scan.py
sunspecdemo/utils.py
sunspecdemo/write.py
sunspecdemo-1.2.301.dist-info/entry_points.txt
sunspecdemo-1.2.301.dist-info/LICENSE
sunspecdemo-1.2.301.dist-info/WHEEL
sunspecdemo-1.2.301.dist-info/METADATA
sunspecdemo-1.2.301.dist-info/RECORD
