Metadata-Version: 2.1
Name: sunspecdemo
Version: 1.2.301
Summary: EPC SunSpec demonstration tool
License: MIT
Author: Alex Anker
Author-email: alex.anker@epcpower.com
Requires-Python: >=3.7.9,<4.0.0
Classifier: License :: OSI Approved :: MIT License
Classifier: Programming Language :: Python :: 3
Classifier: Programming Language :: Python :: 3.10
Classifier: Programming Language :: Python :: 3.8
Classifier: Programming Language :: Python :: 3.9
Requires-Dist: attrs (>=19.3.0)
Requires-Dist: click (>=7.0,<8.0)
Requires-Dist: importlib (>=1.0.4,<2.0.0)
Requires-Dist: importlib-metadata (>=4.10.1,<5.0.0)
Requires-Dist: pyserial (==3.4)
Requires-Dist: pysunspec (==2.1.0)
Requires-Dist: toml (>=0.10.2,<0.11.0)
Requires-Dist: toolz (==0.9.0)
Requires-Dist: tqdm (==4.32.1)
Requires-Dist: typing-extensions (>=4.0.1,<5.0.0)
